pyproject_freeze/__init__.py
pyproject_freeze/freeze.py
pyproject_freeze-0.1.1.dist-info/METADATA
pyproject_freeze-0.1.1.dist-info/WHEEL
pyproject_freeze-0.1.1.dist-info/entry_points.txt
pyproject_freeze-0.1.1.dist-info/top_level.txt
pyproject_freeze-0.1.1.dist-info/RECORD
