Metadata-Version: 2.1
Name: pyproject-freeze
Version: 0.1.1
Summary: pip freeze for pyproject.toml
Author-email: James Munsch <james.a.munsch@gmail.com>
License: MIT
Project-URL: Homepage, https://github.com/allen-munsch/pyproject-freeze
Project-URL: Issues, https://github.com/allen-munsch/pyproject-freeze/issues
Requires-Python: >=3.12
Requires-Dist: pip ==24.2
Requires-Dist: tomlkit ==0.13.2
